olympus/__init__.py
olympus/_version.py
olympus/olympus.py
olympus/.scratch/olympus_01198379.sqlite
olympus/.scratch/olympus_09576ab3.sqlite
olympus/.scratch/olympus_0ac54a60.sqlite
olympus/.scratch/olympus_0e1ad924.sqlite
olympus/.scratch/olympus_14fa7c3a.sqlite
olympus/.scratch/olympus_1715d28f.sqlite
olympus/.scratch/olympus_18753a91.sqlite
olympus/.scratch/olympus_27a17b6d.sqlite
olympus/.scratch/olympus_2a6c1f9d.sqlite
olympus/.scratch/olympus_2d07e41e.sqlite
olympus/.scratch/olympus_316f8c3f.sqlite
olympus/.scratch/olympus_3528aa9d.sqlite
olympus/.scratch/olympus_403bef16.sqlite
olympus/.scratch/olympus_444a9131.sqlite
olympus/.scratch/olympus_67fe604b.sqlite
olympus/.scratch/olympus_8743cf54.sqlite
olympus/.scratch/olympus_d95575ae.sqlite
olympus/.scratch/olympus_d9b8380f.sqlite
olympus/.scratch/olympus_e378283e.sqlite
olympus/.scratch/olympus_f31613c7.sqlite
olympus/__pycache__/__init__.cpython-37.pyc
olympus/__pycache__/_version.cpython-37.pyc
olympus/__pycache__/olympus.cpython-37.pyc
olympus/analyzer/__init__.py
olympus/analyzer/analyzer.py
olympus/analyzer/__pycache__/__init__.cpython-37.pyc
olympus/analyzer/__pycache__/analyzer.cpython-37.pyc
olympus/baseline/__init__.py
olympus/baseline/baseline.py
olympus/baseline/random_search_summary.pkl
olympus/baseline/__pycache__/__init__.cpython-37.pyc
olympus/baseline/__pycache__/baseline.cpython-37.pyc
olympus/campaigns/__init__.py
olympus/campaigns/campaign.py
olympus/campaigns/observations.py
olympus/campaigns/param_space.py
olympus/campaigns/__pycache__/__init__.cpython-37.pyc
olympus/campaigns/__pycache__/campaign.cpython-37.pyc
olympus/campaigns/__pycache__/observations.cpython-37.pyc
olympus/campaigns/__pycache__/param_space.cpython-37.pyc
olympus/cli/__BACKUP_action_olympus.py
olympus/cli/__BACKUP_analyze.py
olympus/cli/__init__.py
olympus/cli/cli_baseline.py
olympus/cli/cli_download.py
olympus/cli/cli_upload.py
olympus/cli/connector_github.py
olympus/cli/connector_server.py
olympus/cli/main.py
olymp-0.0.1b0.dist-info/LICENSE
olymp-0.0.1b0.dist-info/METADATA
olymp-0.0.1b0.dist-info/WHEEL
olymp-0.0.1b0.dist-info/entry_points.txt
olymp-0.0.1b0.dist-info/top_level.txt
olymp-0.0.1b0.dist-info/RECORD
